<?xml version="1.0" encoding="UTF-8"?>
<window type="buttonMenu" id="1113">
    <defaultcontrol>6789</defaultcontrol>
    <include>DialogOpenClose</include>
    <controls>
        <control type="image" description="BG">
            <animation effect="fade" start="0" end="50" delay="150" time="300">WindowOpen</animation>
            <animation effect="fade" start="50" end="0" time="50">WindowClose</animation>
            <width>1920</width>
            <height>1080</height>
            <texture colordiffuse="white">images/White.png</texture>
        </control>
        <control type="image" description="Dialog">
            <centerleft>960</centerleft>
            <centertop>540</centertop>
            <width>1920</width>
            <height>1080</height>
            <aspectratio>stretch</aspectratio>
            <texture border="150">images/Dialog.png</texture>
        </control>
        <control type="textbox">
            <centerleft>960</centerleft>
            <top>200</top>
            <width>1400</width>
            <height>620</height>
            <align>justify</align>
            <label>$LOCALIZE[31414]</label>
        </control>
        <control type="grouplist">
            <centerleft>960</centerleft>
            <top>850</top>
            <width>1200</width>
            <height>81</height>
            <align>center</align>
            <orientation>horizontal</orientation>
            <control type="button" id="6789">
                <width>450</width>
                <height>81</height>
                <onclick>close</onclick>
                <onclick>Skin.ToggleSetting(splashoff)</onclick>
                <label>OK. got it.</label>
            </control>
            <control type="button" id="2">
                <width>450</width>
                <height>81</height>
                <onclick>close</onclick>
                <label>Show Again next time.</label>
            </control>
        </control>
    </controls>
</window>